datacosmos/__init__.py
datacosmos/datacosmos_client.py
datacosmos/auth/__init__.py
datacosmos/auth/base_authenticator.py
datacosmos/auth/local_authenticator.py
datacosmos/auth/local_token_fetcher.py
datacosmos/auth/m2m_authenticator.py
datacosmos/auth/token.py
datacosmos/config/__init__.py
datacosmos/config/config.py
datacosmos/config/constants.py
datacosmos/config/auth/__init__.py
datacosmos/config/auth/factory.py
datacosmos/config/loaders/yaml_source.py
datacosmos/config/models/__init__.py
datacosmos/config/models/authentication_config.py
datacosmos/config/models/local_user_account_authentication_config.py
datacosmos/config/models/m2m_authentication_config.py
datacosmos/config/models/no_authentication_config.py
datacosmos/config/models/url.py
datacosmos/exceptions/__init__.py
datacosmos/exceptions/authentication_error.py
datacosmos/exceptions/datacosmos_error.py
datacosmos/exceptions/http_error.py
datacosmos/exceptions/stac_validation_error.py
datacosmos/exceptions/upload_error.py
datacosmos/stac/__init__.py
datacosmos/stac/stac_client.py
datacosmos/stac/collection/__init__.py
datacosmos/stac/collection/collection_client.py
datacosmos/stac/collection/models/__init__.py
datacosmos/stac/collection/models/collection_update.py
datacosmos/stac/constants/__init__.py
datacosmos/stac/constants/satellite_name_mapping.py
datacosmos/stac/enums/__init__.py
datacosmos/stac/enums/processing_level.py
datacosmos/stac/enums/product_type.py
datacosmos/stac/enums/season.py
datacosmos/stac/item/__init__.py
datacosmos/stac/item/item_client.py
datacosmos/stac/item/models/__init__.py
datacosmos/stac/item/models/asset.py
datacosmos/stac/item/models/catalog_search_parameters.py
datacosmos/stac/item/models/datacosmos_item.py
datacosmos/stac/item/models/eo_band.py
datacosmos/stac/item/models/item_update.py
datacosmos/stac/item/models/raster_band.py
datacosmos/stac/storage/__init__.py
datacosmos/stac/storage/downloader.py
datacosmos/stac/storage/storage_base.py
datacosmos-0.0.27.dist-info/licenses/LICENSE.md
datacosmos-0.0.27.dist-info/METADATA
datacosmos-0.0.27.dist-info/WHEEL
datacosmos-0.0.27.dist-info/top_level.txt
datacosmos-0.0.27.dist-info/RECORD
