Metadata-Version: 2.4
Name: datacosmos
Version: 0.0.27
Summary: A library for interacting with DataCosmos from Python code
Author-email: Open Cosmos <support@open-cosmos.com>
Classifier: Programming Language :: Python :: 3
Classifier: Operating System :: OS Independent
Requires-Python: >=3.10
License-File: LICENSE.md
Requires-Dist: pydantic_settings>=2.7.0
Requires-Dist: requests==2.31.0
Requires-Dist: oauthlib==3.2.0
Requires-Dist: requests-oauthlib==2
Requires-Dist: pydantic>=2
Requires-Dist: pystac==1.12.1
Requires-Dist: pyyaml==6.0.2
Requires-Dist: structlog==24.4.0
Requires-Dist: tenacity>=8.2.3
Requires-Dist: shapely>=1.8.0
Provides-Extra: dev
Requires-Dist: black==22.3.0; extra == "dev"
Requires-Dist: ruff==0.9.5; extra == "dev"
Requires-Dist: pytest==7.2.0; extra == "dev"
Requires-Dist: bandit[toml]==1.7.4; extra == "dev"
Requires-Dist: pbr>=6.0.0; extra == "dev"
Requires-Dist: isort==5.11.4; extra == "dev"
Requires-Dist: pydocstyle==6.1.1; extra == "dev"
Dynamic: license-file
